unholster_inbox/__init__.py
unholster_inbox/inbox.py
unholster_inbox-0.1.1.dist-info/WHEEL
unholster_inbox-0.1.1.dist-info/METADATA
unholster_inbox-0.1.1.dist-info/RECORD
