Metadata-Version: 2.1
Name: unholster-inbox
Version: 0.1.1
Summary: 
Author: Sebastián Acuña
Author-email: sebastian@unholster.com
Requires-Python: >=3.6,<4.0
Classifier: Programming Language :: Python :: 3
Classifier: Programming Language :: Python :: 3.6
Classifier: Programming Language :: Python :: 3.7
Classifier: Programming Language :: Python :: 3.8
Requires-Dist: aws (>=0.2.5,<0.3.0)
Requires-Dist: boto3 (>=1.12.23,<2.0.0)
Requires-Dist: click (>=7.1.1,<8.0.0)
